mockapi/__init__.py
mockapi/__main__.py
mockapi-0.0.1.dist-info/DESCRIPTION.rst
mockapi-0.0.1.dist-info/METADATA
mockapi-0.0.1.dist-info/RECORD
mockapi-0.0.1.dist-info/WHEEL
mockapi-0.0.1.dist-info/entry_points.txt
mockapi-0.0.1.dist-info/metadata.json
mockapi-0.0.1.dist-info/top_level.txt
